odoo/addons/document_page_reference/README.rst
odoo/addons/document_page_reference/__init__.py
odoo/addons/document_page_reference/__manifest__.py
odoo/addons/document_page_reference/i18n/document_page_reference.pot
odoo/addons/document_page_reference/i18n/es.po
odoo/addons/document_page_reference/i18n/it.po
odoo/addons/document_page_reference/i18n/pt.po
odoo/addons/document_page_reference/migrations/18.0.1.1.0/post-migration.py
odoo/addons/document_page_reference/models/__init__.py
odoo/addons/document_page_reference/models/document_page.py
odoo/addons/document_page_reference/readme/CONTRIBUTORS.md
odoo/addons/document_page_reference/readme/DESCRIPTION.md
odoo/addons/document_page_reference/readme/USAGE.md
odoo/addons/document_page_reference/static/description/icon.png
odoo/addons/document_page_reference/static/description/index.html
odoo/addons/document_page_reference/static/src/js/editor.esm.js
odoo/addons/document_page_reference/tests/__init__.py
odoo/addons/document_page_reference/tests/test_document_reference.py
odoo/addons/document_page_reference/views/document_page.xml
odoo/addons/document_page_reference/views/report_document_page.xml
odoo_addon_document_page_reference-18.0.2.0.0.dist-info/METADATA
odoo_addon_document_page_reference-18.0.2.0.0.dist-info/WHEEL
odoo_addon_document_page_reference-18.0.2.0.0.dist-info/top_level.txt
odoo_addon_document_page_reference-18.0.2.0.0.dist-info/RECORD
